take_resolution/__init__.py
take_resolution/run.py
take_resolution/core/__init__.py
take_resolution/core/metrics.py
take_resolution/data_validation/__init__.py
take_resolution/data_validation/main.py
take_resolution/data_validation/run_input_validation.py
test/__init__.py
test/test_run.py
take_resolution-1.0.0.dist-info/LICENSE
take_resolution-1.0.0.dist-info/METADATA
take_resolution-1.0.0.dist-info/WHEEL
take_resolution-1.0.0.dist-info/top_level.txt
take_resolution-1.0.0.dist-info/RECORD
