Metadata-Version: 2.1
Name: take-resolution
Version: 1.0.0
Summary: Generate a rate between 0 and 1 for Resolution rate on smart contacts.
Home-page: UNKNOWN
Author: squad XD
Author-email: anaytics.ped@take.net
Maintainer: Take - D&A
Maintainer-email: anaytics.ped@take.net
License: MIT License
Keywords: BLiP,score,resolution
Platform: UNKNOWN
Classifier: Programming Language :: Python :: 3.7
Classifier: Operating System :: OS Independent
Requires-Python: >=3.6
Requires-Dist: numpy (==1.19.4)
Requires-Dist: pandas (==1.1.4)
